Workbook

Sheet README
A1: THE UNLOX ACADEMY - DA/DS TRACK
A2: Excel Minor Project - Sales Operations Analytics
A3: Interview-Grade Data Analytics Assessment · 100 Marks
A5: THE SCENARIO
A6: You have just joined the analytics team at a fast-growing multi-category retailer operating across 6 Indian cities.
A7: The head of sales has handed you 5 raw data files - Orders, Customers, Products, Sales Reps, and Targets - and asked
A8: you to answer a set of business questions before the leadership review tomorrow morning.
A10: The data is REAL-WORLD messy: duplicates, missing references, inconsistent case, invalid records, discontinued SKUs.
A11: Part of the assessment is spotting and handling these issues correctly. A wrong-looking answer isn't always wrong -
A12: sometimes the data itself is telling a story.
A14: RULES OF THE ASSESSMENT
A15: 1. Write your answer in the YELLOW cells on each question sheet. Empty answer cell = 0 marks.
... A22: MARKS DISTRIBUTION
A23: Section | B23: Topic | C23: Questions | D23: Marks
A24: Q1 | B24: Lookup Functions (VLOOKUP, INDEX-MATCH, chained lookups) | C24: 8 | D24: 25
A25: Q2 | B25: Data Cleaning & Quality Diagnostics | C25: 6 | D25: 20
A26: Q3 | B26: Conditional Aggregation (SUMIFS, COUNTIFS, IF logic) | C26: 6 | D26: 25
A27: Q4 | B27: Pivot Tables (2D pivots, % of total, calculated fields) | C27: 5 | D27: 20
A28: Q5 | B28: Advanced (Ranking, Running Totals, Multi-condition) | C28: 5 | D28: 10
B29: TOTAL | C29: 30 | D29: 100
A32: PERFORMANCE TIERS
A33: Marks | B33: Tier | C33: Interview Verdict
A34: 85 - 100 | B34: Excellent | C34: Round 1 clear - Excel not a concern
A35: 70 - 84 | B35: Good | C35: Round 1 clear with minor gaps
A36: 55 - 69 | B36: Borderline | C36: Round 1 uncertain - needs revision
A37: 40 - 54 | B37: Weak | C37: Round 1 likely reject - 2 weeks of practice needed
A38: < 40 | B38: Insufficient | C38: Round 1 reject - foundational gaps
A41: DATA SHEETS OVERVIEW
A42: Sheet | B42: Rows | C42: Key Columns | D42: Joins to
A43: Orders | B43: ~2000 | C43: order_id, order_date, customer_id, product_id, sales_rep_id, quantity, unit_price, discount_pct, final_amount, payment_status, ship_city | D43: All others
A44: Customers | B44: 300 | C44: customer_id (PK), customer_name, age, city, segment, signup_date | D44: Orders via customer_id
A45: Products | B45: 60 | C45: product_id (PK), product_name, category, unit_cost, unit_price, is_active | D45: Orders via product_id
A46: Sales_Reps | B46: 30 | C46: rep_id (PK), rep_name, region, hire_date, team_lead_id | D46: Orders via sales_rep_id, self-join via team_lead_id
A47: Targets | B47: 30 × 12 | C47: rep_id (PK), Jan-24 through Dec-24 monthly target values | D47: Sales_Reps via rep_id

Sheet Sheet1
A3: Sum of final_amount | B3: Column Labels
A4: Row Labels | B4: Apparel | C4: Beauty | D4: Electronics | E4: Grocery | F4: Home | G4: Sports | H4: (blank) | I4: Grand Total
A5: East | B5: 860762.23 | C5: 1271152.8 | D5: 1214881.9 | E5: 1168089.9 | F5: 1124233.5 | G5: 945710.08 | I5: 6584830.5
A6: North | B6: 979380.97 | C6: 1556120.2 | D6: 1450710.7 | E6: 1118963.8 | F6: 867033.27 | G6: 1011820.5 | I6: 6984029.5
A7: South | B7: 962768.31 | C7: 1590646.1 | D7: 1314107.4 | E7: 1041400.8 | F7: 1140277.8 | G7: 1095843.5 | I7: 7145043.8
A8: West | B8: 868240.03 | C8: 1188460 | D8: 993053.05 | E8: 997265.82 | F8: 955407.58 | G8: 856617.89 | I8: 5859044.4
A9: (blank)
A10: Grand Total | B10: 3671151.5 | C10: 5606379.1 | D10: 4972753.1 | E10: 4325720.4 | F10: 4086952.2 | G10: 3909991.9 | I10: 26572948

Sheet Sheet3
A3: Sum of final_amount | B3: Column Labels
A4: Row Labels | B4: R001 | C4: R002 | D4: R003 | E4: R004 | F4: R005 | G4: R006 | H4: R007 | I4: R008 | J4: R009 | K4: R010 | L4: R011 | M4: R012 | N4: R013 | O4: R014 | P4: R015 | Q4: R016 | R4: R017 | S4: R018 | T4: R019 | U4: R020 | V4: R021 | W4: R022 | X4: R023 | Y4: R024 | Z4: R025 | AA4: R026 | AB4: R027 | AC4: R028 | AD4: R029 | AE4: R030 | AF4: (blank) | AG4: Grand Total
A5: (blank)
A6: Qtr1 | B6: 228864.22 | C6: 230428.1 | D6: 194248.23 | E6: 131105.05 | F6: 214433.75 | G6: 264985.68 | H6: 327795.78 | I6: 249635.37 | J6: 170613.48 | K6: 117633.85 | L6: 279577.54 | M6: 201325.73 | N6: 270851.64 | O6: 252597.58 | P6: 276393.23 | Q6: 306613.53 | R6: 221447.89 | S6: 274596.56 | T6: 197363.06 | U6: 271016.56 | V6: 208037.59 | W6: 256354.31 | X6: 257909.53 | Y6: 186754.87 | Z6: 230773.26 | AA6: 98119.44 | AB6: 194517.49 | AC6: 165250.06 | AD6: 251234.19 | AE6: 198486.16 | AG6: 6728963.7
A7: Qtr2 | B7: 161243.09 | C7: 218835.15 | D7: 273573.67 | E7: 206164.46 | F7: 226933.7 | G7: 440513.99 | H7: 148589.13 | I7: 161726.57 | J7: 244591.35 | K7: 154589.16 | L7: 86566.7 | M7: 121352.71 | N7: 156044.5 | O7: 271638.97 | P7: 266652.96 | Q7: 198824.31 | R7: 219786.14 | S7: 501552.87 | T7: 278748.68 | U7: 323625.36 | V7: 193123.4 | W7: 163521.45 | X7: 359180.9 | Y7: 235404.88 | Z7: 176207 | AA7: 180328.8 | AB7: 212478.47 | AC7: 161616.1 | AD7: 333952.82 | AE7: 151416.93 | AG7: 6828784.2
A8: Qtr3 | B8: 210322.46 | C8: 289097.53 | D8: 370474.74 | E8: 110743.1 | F8: 117673.32 | G8: 176965.05 | H8: 133919.19 | I8: 186301.55 | J8: 314054.99 | K8: 353444.84 | L8: 249319.24 | M8: 294920.4 | N8: 166680.93 | O8: 234411.6 | P8: 258884.58 | Q8: 224009.94 | R8: 168425.67 | S8: 96924.94 | T8: 127630.06 | U8: 194229.76 | V8: 224789.09 | W8: 380043.1 | X8: 190111.17 | Y8: 141698.82 | Z8: 323095.54 | AA8: 129536.87 | AB8: 184503.15 | AC8: 300623.19 | AD8: 213202.16 | AE8: 189720.29 | AG8: 6555757.3
A9: Qtr4 | B9: 189419.83 | C9: 241702.88 | D9: 148396.27 | E9: 141013.68 | F9: 223404.56 | G9: 256184.01 | H9: 245445.58 | I9: 263889.84 | J9: 185294.9 | K9: 254677.35 | L9: 119744.28 | M9: 283795.48 | N9: 217947.31 | O9: 237065.39 | P9: 289809.41 | Q9: 85115.93 | R9: 170724.71 | S9: 239215.27 | T9: 367441.72 | U9: 117236.03 | V9: 135557.09 | W9: 269651.68 | X9: 176585.88 | Y9: 255700.01 | Z9: 171223.09 | AA9: 168319.97 | AB9: 325593.51 | AC9: 252978.7 | AD9: 218307.63 | AE9: 208000.99 | AG9: 6459443
A10: Grand Total | B10: 789849.6 | C10: 980063.66 | D10: 986692.91 | E10: 589026.29 | F10: 782445.33 | G10: 1138648.7 | H10: 855749.68 | I10: 861553.33 | J10: 914554.72 | K10: 880345.2 | L10: 735207.76 | M10: 901394.32 | N10: 811524.38 | O10: 995713.54 | P10: 1091740.2 | Q10: 814563.71 | R10: 780384.41 | S10: 1112289.6 | T10: 971183.52 | U10: 906107.71 | V10: 761507.17 | W10: 1069570.5 | X10: 983787.48 | Y10: 819558.58 | Z10: 901298.89 | AA10: 576305.08 | AB10: 917092.62 | AC10: 880468.05 | AD10: 1016696.8 | AE10: 747624.37 | AG10: 26572948
C21: =MAX(B6:AE17) -> 1138648.7

Sheet Sheet5
A1: Region_Helper | B1: West
A3: Row Labels | B3: Sum of final_amount
A4: PROD-056 | B4: 260395.74
A5: PROD-003 | B5: 248025.75
A6: PROD-048 | B6: 244351.2
A7: PROD-034 | B7: 221112.08
A8: PROD-004 | B8: 198124.65
A9: PROD-025 | B9: 190994.58
A10: PROD-026 | B10: 179739.34
A11: PROD-039 | B11: 177512.66
A12: PROD-047 | B12: 167780.4
A13: PROD-001 | B13: 155358.84
A14: PROD-059 | B14: 150054.66
A15: PROD-011 | B15: 145224.3
... A64: Grand Total | B64: 5859044.4

Sheet Orders
A1: order_id | B1: order_date | C1: customer_id | D1: product_id | E1: sales_rep_id | F1: quantity | G1: unit_price | H1: discount_pct | I1: final_amount | J1: payment_status | K1: ship_city | L1: Category_Helper | M1: Segment_Helper | N1: Age_Helper | O1: Region_Helper | P1: Unit_Cost | Q1: Profit_Margin
A2: ORD-00001 | B2: 45549 | C2: CUST-0243 | D2: PROD-014 | E2: R007 | F2: 8 | G2: 3620 | H2: 15.4 | I2: 24500.16 | J2: Completed | K2: Pune | L2: =IFERROR(VLOOKUP(D2,Products!$A:$C,3,FALSE),"") -> Apparel | M2: =IFERROR(VLOOKUP(C2,Customers!$A:$E,5,FALSE),"") -> SMB | N2: =IFERROR(VLOOKUP(C2,Customers!$A:$E,3,FALSE),"") -> 44 | O2: =IFERROR(VLOOKUP(E2,Sales_Reps!$A:$C,3,FALSE),"") -> North | P2: =IFERROR(VLOOKUP(D2,Products!$A:$D,4,FALSE),"") -> 2509 | Q2: =IFERROR((G2-P2)/G2,"") -> 0.30690608
A3: ORD-00002 | B3: 45340 | C3: CUST-0202 | D3: PROD-020 | E3: R005 | F3: 2 | G3: 820 | H3: 10.8 | I3: 1462.88 | J3: Pending | K3: Chennai | L3: =IFERROR(VLOOKUP(D3,Products!$A:$C,3,FALSE),"") -> Apparel | M3: =IFERROR(VLOOKUP(C3,Customers!$A:$E,5,FALSE),"") -> Retail | N3: =IFERROR(VLOOKUP(C3,Customers!$A:$E,3,FALSE),"") -> 39 | O3: =IFERROR(VLOOKUP(E3,Sales_Reps!$A:$C,3,FALSE),"") -> North | P3: =IFERROR(VLOOKUP(D3,Products!$A:$D,4,FALSE),"") -> 391 | Q3: =IFERROR((G3-P3)/G3,"") -> 0.52317073
A4: ORD-00003 | B4: 45371 | C4: CUST-0098 | D4: PROD-053 | E4: R014 | F4: 8 | G4: 470 | H4: 3.3 | I4: 3635.92 | J4: Pending | K4: Delhi | L4: =IFERROR(VLOOKUP(D4,Products!$A:$C,3,FALSE),"") -> Sports | M4: =IFERROR(VLOOKUP(C4,Customers!$A:$E,5,FALSE),"") -> Retail | N4: =IFERROR(VLOOKUP(C4,Customers!$A:$E,3,FALSE),"") -> 52 | O4: =IFERROR(VLOOKUP(E4,Sales_Reps!$A:$C,3,FALSE),"") -> South | P4: =IFERROR(VLOOKUP(D4,Products!$A:$D,4,FALSE),"") -> 302 | Q4: =IFERROR((G4-P4)/G4,"") -> 0.35744681
A5: ORD-00004 | B5: 45413 | C5: CUST-0071 | D5: PROD-028 | E5: R006 | F5: 1 | G5: 3660 | H5: 15.7 | I5: 3085.38 | J5: Completed | K5: Delhi | L5: =IFERROR(VLOOKUP(D5,Products!$A:$C,3,FALSE),"") -> Grocery | M5: =IFERROR(VLOOKUP(C5,Customers!$A:$E,5,FALSE),"") -> Corporate | N5: =IFERROR(VLOOKUP(C5,Customers!$A:$E,3,FALSE),"") -> 46 | O5: =IFERROR(VLOOKUP(E5,Sales_Reps!$A:$C,3,FALSE),"") -> North | P5: =IFERROR(VLOOKUP(D5,Products!$A:$D,4,FALSE),"") -> 2214 | Q5: =IFERROR((G5-P5)/G5,"") -> 0.39508197
A6: ORD-00005 | B6: 45611 | C6: CUST-0180 | D6: PROD-012 | E6: R008 | F6: 1 | G6: 3160 | H6: 26 | I6: 2338.4 | J6: Completed | K6: Chennai | L6: =IFERROR(VLOOKUP(D6,Products!$A:$C,3,FALSE),"") -> Apparel | M6: =IFERROR(VLOOKUP(C6,Customers!$A:$E,5,FALSE),"") -> Retail | N6: =IFERROR(VLOOKUP(C6,Customers!$A:$E,3,FALSE),"") -> 36 | O6: =IFERROR(VLOOKUP(E6,Sales_Reps!$A:$C,3,FALSE),"") -> North | P6: =IFERROR(VLOOKUP(D6,Products!$A:$D,4,FALSE),"") -> 1886 | Q6: =IFERROR((G6-P6)/G6,"") -> 0.40316456
A7: ORD-00006 | B7: 45406 | C7: CUST-0275 | D7: PROD-032 | E7: R025 | F7: 4 | G7: 370 | H7: 29 | I7: 1050.8 | J7: Completed | K7: Mumbai | L7: =IFERROR(VLOOKUP(D7,Products!$A:$C,3,FALSE),"") -> Home | M7: =IFERROR(VLOOKUP(C7,Customers!$A:$E,5,FALSE),"") -> Retail | N7: =IFERROR(VLOOKUP(C7,Customers!$A:$E,3,FALSE),"") -> 36 | O7: =IFERROR(VLOOKUP(E7,Sales_Reps!$A:$C,3,FALSE),"") -> West | P7: =IFERROR(VLOOKUP(D7,Products!$A:$D,4,FALSE),"") -> 288 | Q7: =IFERROR((G7-P7)/G7,"") -> 0.22162162
A8: ORD-00007 | B8: 45455 | C8: CUST-0293 | D8: PROD-057 | E8: R024 | F8: 3 | G8: 960 | H8: 5.8 | I8: 2712.96 | J8: Completed | K8: Bengaluru | L8: =IFERROR(VLOOKUP(D8,Products!$A:$C,3,FALSE),"") -> Sports | M8: =IFERROR(VLOOKUP(C8,Customers!$A:$E,5,FALSE),"") -> Retail | N8: =IFERROR(VLOOKUP(C8,Customers!$A:$E,3,FALSE),"") -> 27 | O8: =IFERROR(VLOOKUP(E8,Sales_Reps!$A:$C,3,FALSE),"") -> West | P8: =IFERROR(VLOOKUP(D8,Products!$A:$D,4,FALSE),"") -> 705 | Q8: =IFERROR((G8-P8)/G8,"") -> 0.265625
A9: ORD-00008 | B9: 45617 | C9: CUST-0281 | D9: PROD-007 | E9: R019 | F9: 8 | G9: 1430 | H9: 2.4 | I9: 11165.44 | J9: Completed | K9: Bengaluru | L9: =IFERROR(VLOOKUP(D9,Products!$A:$C,3,FALSE),"") -> Electronics | M9: =IFERROR(VLOOKUP(C9,Customers!$A:$E,5,FALSE),"") -> Corporate | N9: =IFERROR(VLOOKUP(C9,Customers!$A:$E,3,FALSE),"") -> 57 | O9: =IFERROR(VLOOKUP(E9,Sales_Reps!$A:$C,3,FALSE),"") -> East | P9: =IFERROR(VLOOKUP(D9,Products!$A:$D,4,FALSE),"") -> 861 | Q9: =IFERROR((G9-P9)/G9,"") -> 0.3979021
A10: ORD-00009 | B10: 45549 | C10: CUST-0260 | D10: PROD-038 | E10: R008 | F10: 3 | G10: 5490 | H10: 14.2 | I10: 14131.26 | J10: Completed | K10: Bengaluru | L10: =IFERROR(VLOOKUP(D10,Products!$A:$C,3,FALSE),"") -> Home | M10: =IFERROR(VLOOKUP(C10,Customers!$A:$E,5,FALSE),"") -> Retail | N10: =IFERROR(VLOOKUP(C10,Customers!$A:$E,3,FALSE),"") -> 42 | O10: =IFERROR(VLOOKUP(E10,Sales_Reps!$A:$C,3,FALSE),"") -> North | P10: =IFERROR(VLOOKUP(D10,Products!$A:$D,4,FALSE),"") -> 2549 | Q10: =IFERROR((G10-P10)/G10,"") -> 0.53570128
A11: ORD-00010 | B11: 45396 | C11: CUST-0147 | D11: PROD-030 | E11: R028 | F11: 3 | G11: 970 | H11: 1.2 | I11: 2875.08 | J11: Completed | K11: Pune | L11: =IFERROR(VLOOKUP(D11,Products!$A:$C,3,FALSE),"") -> Grocery | M11: =IFERROR(VLOOKUP(C11,Customers!$A:$E,5,FALSE),"") -> Retail | N11: =IFERROR(VLOOKUP(C11,Customers!$A:$E,3,FALSE),"") -> 56 | O11: =IFERROR(VLOOKUP(E11,Sales_Reps!$A:$C,3,FALSE),"") -> West | P11: =IFERROR(VLOOKUP(D11,Products!$A:$D,4,FALSE),"") -> 434 | Q11: =IFERROR((G11-P11)/G11,"") -> 0.55257732
A12: ORD-00011 | B12: 45560 | C12: CUST-0204 | D12: PROD-024 | E12: R010 | F12: 7 | G12: 2270 | H12: 7.1 | I12: 14761.81 | J12: Pending | K12: Hyderabad | L12: =IFERROR(VLOOKUP(D12,Products!$A:$C,3,FALSE),"") -> Grocery | M12: =IFERROR(VLOOKUP(C12,Customers!$A:$E,5,FALSE),"") -> Retail | N12: =IFERROR(VLOOKUP(C12,Customers!$A:$E,3,FALSE),"") -> 60 | O12: =IFERROR(VLOOKUP(E12,Sales_Reps!$A:$C,3,FALSE),"") -> South | P12: =IFERROR(VLOOKUP(D12,Products!$A:$D,4,FALSE),"") -> 1203 | Q12: =IFERROR((G12-P12)/G12,"") -> 0.47004405
A13: ORD-00012 | B13: 45332 | C13: CUST-0147 | D13: PROD-010 | E13: R024 | F13: 9 | G13: 2640 | H13: 21.7 | I13: 18604.08 | J13: Completed | K13: Pune | L13: =IFERROR(VLOOKUP(D13,Products!$A:$C,3,FALSE),"") -> Electronics | M13: =IFERROR(VLOOKUP(C13,Customers!$A:$E,5,FALSE),"") -> Retail | N13: =IFERROR(VLOOKUP(C13,Customers!$A:$E,3,FALSE),"") -> 56 | O13: =IFERROR(VLOOKUP(E13,Sales_Reps!$A:$C,3,FALSE),"") -> West | P13: =IFERROR(VLOOKUP(D13,Products!$A:$D,4,FALSE),"") -> 1149 | Q13: =IFERROR((G13-P13)/G13,"") -> 0.56477273
... A2001: ORD-02000 | B2001: 45325 | C2001: CUST-0238 | D2001: PROD-034 | E2001: R023 | F2001: 6 | G2001: 5080 | H2001: 28.1 | I2001: 21915.12 | J2001: Completed | K2001: Delhi | L2001: =IFERROR(VLOOKUP(D2001,Products!$A:$C,3,FALSE),"") -> Home | M2001: =IFERROR(VLOOKUP(C2001,Customers!$A:$E,5,FALSE),"") -> Retail | N2001: =IFERROR(VLOOKUP(C2001,Customers!$A:$E,3,FALSE),"") -> 49 | O2001: =IFERROR(VLOOKUP(E2001,Sales_Reps!$A:$C,3,FALSE),"") -> East | P2001: =IFERROR(VLOOKUP(D2001,Products!$A:$D,4,FALSE),"") -> 2459 | Q2001: =IFERROR((G2001-P2001)/G2001,"") -> 0.51594488
N2002: =IFERROR(VLOOKUP(C2002,Customers!$A:$E,3,FALSE),"") | P2002: =IFERROR(VLOOKUP(D2002,Products!$A:$D,4,FALSE),"")
N2003: =IFERROR(VLOOKUP(C2003,Customers!$A:$E,3,FALSE),"") | P2003: =IFERROR(VLOOKUP(D2003,Products!$A:$D,4,FALSE),"")
N2004: =AVERAGEIF(Orders!$K$2:$K$2001,"Delhi",Orders!$Q$2:$Q$2001) -> 0.44880873 | P2004: =IFERROR(VLOOKUP(D2004,Products!$A:$D,4,FALSE),"")
N2005: =IFERROR(VLOOKUP(C2005,Customers!$A:$E,3,FALSE),"") | P2005: =IFERROR(VLOOKUP(D2005,Products!$A:$D,4,FALSE),"")
P2006: =IFERROR(VLOOKUP(D2006,Products!$A:$D,4,FALSE),"")
P2007: =IFERROR(VLOOKUP(D2007,Products!$A:$D,4,FALSE),"")
P2008: =IFERROR(VLOOKUP(D2008,Products!$A:$D,4,FALSE),"")
P2009: =IFERROR(VLOOKUP(D2009,Products!$A:$D,4,FALSE),"")
P2010: =IFERROR(VLOOKUP(D2010,Products!$A:$D,4,FALSE),"")
P2011: =IFERROR(VLOOKUP(D2011,Products!$A:$D,4,FALSE),"")
P2012: =IFERROR(VLOOKUP(D2012,Products!$A:$D,4,FALSE),"")
P2013: =IFERROR(VLOOKUP(D2013,Products!$A:$D,4,FALSE),"")
P2014: =IFERROR(VLOOKUP(D2014,Products!$A:$D,4,FALSE),"")
P2015: =IFERROR(VLOOKUP(D2015,Products!$A:$D,4,FALSE),"")
P2016: =IFERROR(VLOOKUP(D2016,Products!$A:$D,4,FALSE),"")
P2017: =IFERROR(VLOOKUP(D2017,Products!$A:$D,4,FALSE),"")
... P2268: =IFERROR(VLOOKUP(D2268,Products!$A:$D,4,FALSE),"")

Sheet Customers
A1: customer_id | B1: customer_name | C1: age | D1: city | E1: segment | F1: signup_date
A2: CUST-0001 | B2: Amit Agarwal | C2: 36 | D2: Pune | E2: Retail | F2: 44819
A3: CUST-0002 | B3: Vihaan Malhotra | C3: 42 | D3: Pune | E3: Corporate | F3: 44984
A4: CUST-0003 | B4: Navya Malhotra | C4: 33 | D4: Mumbai | E4: Retail | F4: 44059
A5: CUST-0004 | B5: Aaradhya Mehta | C5: 53 | D5: delhi | E5: Retail | F5: 44054
A6: CUST-0005 | B6: Myra Malhotra | C6: 52 | D6: Chennai | E6: Corporate | F6: 45037
A7: CUST-0006 | B7: Shaurya Iyer | C7: 44 | D7: Pune | E7: SMB | F7: 44302
A8: CUST-0007 | B8: Dhruv Joshi | C8: 47 | D8: Bengaluru | E8: Retail | F8: 44498
A9: CUST-0008 | B9: Kavita Malhotra | C9: 39 | D9: Pune | E9: SMB | F9: 45162
A10: CUST-0009 | B10: Neha Malhotra | C10: 61 | D10: Mumbai | E10: Retail | F10: 44343
A11: CUST-0010 | B11: Aaradhya Gupta | C11: 61 | D11: Mumbai | E11: SMB | F11: 44975
A12: CUST-0011 | B12: Diya Menon | C12: 41 | D12: Chennai | E12: Corporate | F12: 44821
A13: CUST-0012 | B13: Prisha Desai | C13: 43 | D13: Pune | E13: Retail | F13: 44718
... A301: CUST-0300 | B301: Rohit Nair | C301: 38 | D301: Mumbai | E301: Retail | F301: 43932

Sheet Products
A1: product_id | B1: product_name | C1: category | D1: unit_cost | E1: unit_price | F1: is_active
A2: PROD-001 | B2: Smartphone Pro | C2: Electronics | D2: 2405 | E2: 5330 | F2: TRUE
A3: PROD-002 | B3: Wireless Earbuds | C3: Electronics | D3: 1052 | E3: 2600 | F3: TRUE
A4: PROD-003 | B4: Smart Watch | C4: Electronics | D4: 1665 | E4: 3570 | F4: TRUE
A5: PROD-004 | B5: Laptop Bag | C5: Electronics | D5: 1559 | E5: 3870 | F5: TRUE
A6: PROD-005 | B6: Power Bank | C6: Electronics | D6: 128 | E6: 300 | F6: TRUE
A7: PROD-006 | B7: Bluetooth Speaker | C7: Electronics | D7: 2865 | E7: 3970 | F7: TRUE
A8: PROD-007 | B8: USB-C Cable | C8: Electronics | D8: 861 | E8: 1430 | F8: TRUE
A9: PROD-008 | B9: Wireless Mouse | C9: Electronics | D9: 1259 | E9: 2660 | F9: FALSE
A10: PROD-009 | B10: Mechanical Keyboard | C10: Electronics | D10: 517 | E10: 1220 | F10: TRUE
A11: PROD-010 | B11: Tablet Stand | C11: Electronics | D11: 1149 | E11: 2640 | F11: TRUE
A12: PROD-011 | B12: Cotton T-Shirt | C12: Apparel | D12: 1748 | E12: 3450 | F12: TRUE
A13: PROD-012 | B13: Denim Jeans | C13: Apparel | D13: 1886 | E13: 3160 | F13: TRUE
... A61: PROD-060 | B61: Gym Gloves | C61: Sports | D61: 147 | E61: 190 | F61: TRUE

Sheet Sales_Reps
A1: rep_id | B1: rep_name | C1: region | D1: hire_date | E1: team_lead_id | H1: Rep ID | I1: Total Revenue | J1: Rank
A2: R001 | B2: Rajesh Malhotra | C2: North | D2: 44207 | H2: R001 | I2: =SUMIF(Orders!$E$2:$E$2001,H2,Orders!$I$2:$I$2001) -> 789849.6 | J2: =_xlfn.RANK.EQ(I2,$I$2:$I$31,0) -> 23
A3: R002 | B3: Sunita Malhotra | C3: North | D3: 44028 | H3: R002 | I3: =SUMIF(Orders!$E$2:$E$2001,H3,Orders!$I$2:$I$2001) -> 980063.66 | J3: =_xlfn.RANK.EQ(I3,$I$2:$I$31,0) -> 9
A4: R003 | B4: Amit Singh | C4: North | D4: 43651 | H4: R003 | I4: =SUMIF(Orders!$E$2:$E$2001,H4,Orders!$I$2:$I$2001) -> 986692.91 | J4: =_xlfn.RANK.EQ(I4,$I$2:$I$31,0) -> 7
A5: R004 | B5: Priya Singh | C5: North | D5: 44907 | H5: R004 | I5: =SUMIF(Orders!$E$2:$E$2001,H5,Orders!$I$2:$I$2001) -> 589026.29 | J5: =_xlfn.RANK.EQ(I5,$I$2:$I$31,0) -> 29
A6: R005 | B6: Vikram Patel | C6: North | D6: 43588 | E6: R001 | H6: R005 | I6: =SUMIF(Orders!$E$2:$E$2001,H6,Orders!$I$2:$I$2001) -> 782445.33 | J6: =_xlfn.RANK.EQ(I6,$I$2:$I$31,0) -> 24
A7: R006 | B7: Neha Desai | C7: North | D7: 44131 | E7: R001 | H7: R006 | I7: =SUMIF(Orders!$E$2:$E$2001,H7,Orders!$I$2:$I$2001) -> 1138648.7 | J7: =_xlfn.RANK.EQ(I7,$I$2:$I$31,0) -> 1
A8: R007 | B8: Suresh Menon | C8: North | D8: 43493 | E8: R001 | H8: R007 | I8: =SUMIF(Orders!$E$2:$E$2001,H8,Orders!$I$2:$I$2001) -> 855749.68 | J8: =_xlfn.RANK.EQ(I8,$I$2:$I$31,0) -> 19
A9: R008 | B9: Kavita Patel | C9: North | D9: 44693 | E9: R001 | H9: R008 | I9: =SUMIF(Orders!$E$2:$E$2001,H9,Orders!$I$2:$I$2001) -> 861553.33 | J9: =_xlfn.RANK.EQ(I9,$I$2:$I$31,0) -> 18
A10: R009 | B10: Manoj Patel | C10: South | D10: 44804 | E10: R002 | H10: R009 | I10: =SUMIF(Orders!$E$2:$E$2001,H10,Orders!$I$2:$I$2001) -> 914554.72 | J10: =_xlfn.RANK.EQ(I10,$I$2:$I$31,0) -> 12
A11: R010 | B11: Divya Rao | C11: South | D11: 43904 | E11: R002 | H11: R010 | I11: =SUMIF(Orders!$E$2:$E$2001,H11,Orders!$I$2:$I$2001) -> 880345.2 | J11: =_xlfn.RANK.EQ(I11,$I$2:$I$31,0) -> 17
A12: R011 | B12: Anil Verma | C12: South | D12: 44622 | E12: R002 | H12: R011 | I12: =SUMIF(Orders!$E$2:$E$2001,H12,Orders!$I$2:$I$2001) -> 735207.76 | J12: =_xlfn.RANK.EQ(I12,$I$2:$I$31,0) -> 28
A13: R012 | B13: Pooja Nair | C13: South | D13: 44890 | E13: R002 | H13: R012 | I13: =SUMIF(Orders!$E$2:$E$2001,H13,Orders!$I$2:$I$2001) -> 901394.32 | J13: =_xlfn.RANK.EQ(I13,$I$2:$I$31,0) -> 14
A14: R013 | B14: Sanjay Kapoor | C14: South | D14: 45215 | E14: R002 | H14: R013 | I14: =SUMIF(Orders!$E$2:$E$2001,H14,Orders!$I$2:$I$2001) -> 811524.38 | J14: =_xlfn.RANK.EQ(I14,$I$2:$I$31,0) -> 22
A15: R014 | B15: Ritu Menon | C15: South | D15: 44469 | E15: R002 | H15: R014 | I15: =SUMIF(Orders!$E$2:$E$2001,H15,Orders!$I$2:$I$2001) -> 995713.54 | J15: =_xlfn.RANK.EQ(I15,$I$2:$I$31,0) -> 6
A16: R015 | B16: Deepak Shah | C16: South | D16: 45231 | E16: R002 | H16: R015 | I16: =SUMIF(Orders!$E$2:$E$2001,H16,Orders!$I$2:$I$2001) -> 1091740.2 | J16: =_xlfn.RANK.EQ(I16,$I$2:$I$31,0) -> 3
A17: R016 | B17: Anjali Chopra | C17: South | D17: 43614 | E17: R002 | H17: R016 | I17: =SUMIF(Orders!$E$2:$E$2001,H17,Orders!$I$2:$I$2001) -> 814563.71 | J17: =_xlfn.RANK.EQ(I17,$I$2:$I$31,0) -> 21
... A31: R030 | B31: Kiran Bhatt | C31: West | D31: 44506 | E31: R004 | H31: R030 | I31: =SUMIF(Orders!$E$2:$E$2001,H31,Orders!$I$2:$I$2001) -> 747624.37 | J31: =_xlfn.RANK.EQ(I31,$I$2:$I$31,0) -> 27

Sheet Targets
A1: rep_id | B1: Jan-24 | C1: Feb-24 | D1: Mar-24 | E1: Apr-24 | F1: May-24 | G1: Jun-24 | H1: Jul-24 | I1: Aug-24 | J1: Sep-24 | K1: Oct-24 | L1: Nov-24 | M1: Dec-24
A2: R001 | B2: 231324 | C2: 171682 | D2: 234376 | E2: 326967 | F2: 350588 | G2: 385324 | H2: 307980 | I2: 327947 | J2: 181016 | K2: 374039 | L2: 212805 | M2: 405999
A3: R002 | B3: 438126 | C3: 346266 | D3: 329993 | E3: 370744 | F3: 294660 | G3: 341556 | H3: 151934 | I3: 223794 | J3: 438641 | K3: 344308 | L3: 296172 | M3: 304288
A4: R003 | B4: 358703 | C4: 320519 | D4: 327321 | E4: 298753 | F4: 254636 | G4: 351929 | H4: 264723 | I4: 216459 | J4: 391945 | K4: 362426 | L4: 289199 | M4: 301863
A5: R004 | B5: 389594 | C5: 376422 | D5: 324156 | E5: 420255 | F5: 409107 | G5: 269954 | H5: 179097 | I5: 370568 | J5: 387395 | K5: 243454 | L5: 232530 | M5: 201999
A6: R005 | B6: 436862 | C6: 391158 | D6: 340224 | E6: 170548 | F6: 229390 | G6: 349525 | H6: 154683 | I6: 320848 | J6: 354452 | K6: 377180 | L6: 342347 | M6: 183362
A7: R006 | B7: 348734 | C7: 358191 | D7: 250385 | E7: 219657 | F7: 249365 | G7: 435704 | H7: 260892 | I7: 250741 | J7: 358402 | K7: 379858 | L7: 213280 | M7: 224634
A8: R007 | B8: 280057 | C8: 330342 | D8: 336856 | E8: 227425 | F8: 233647 | G8: 307088 | H8: 370724 | I8: 440008 | J8: 406347 | K8: 217357 | L8: 299289 | M8: 214568
A9: R008 | B9: 252886 | C9: 206057 | D9: 318209 | E9: 411230 | F9: 448660 | G9: 171135 | H9: 305339 | I9: 432264 | J9: 294273 | K9: 371409 | L9: 284207 | M9: 437068
A10: R009 | B10: 268752 | C10: 393256 | D10: 310649 | E10: 246237 | F10: 271287 | G10: 314545 | H10: 406506 | I10: 334930 | J10: 348625 | K10: 408928 | L10: 243749 | M10: 418409
A11: R010 | B11: 384734 | C11: 156698 | D11: 283679 | E11: 276085 | F11: 409270 | G11: 285230 | H11: 304233 | I11: 178221 | J11: 284216 | K11: 287373 | L11: 229082 | M11: 298969
A12: R011 | B12: 186029 | C12: 151419 | D12: 253251 | E12: 379757 | F12: 204209 | G12: 179396 | H12: 378008 | I12: 182649 | J12: 267772 | K12: 350352 | L12: 358042 | M12: 359960
A13: R012 | B13: 352158 | C13: 251181 | D13: 321255 | E13: 300863 | F13: 241731 | G13: 393275 | H13: 313561 | I13: 283604 | J13: 429065 | K13: 194420 | L13: 254168 | M13: 389283
... A31: R030 | B31: 151584 | C31: 221679 | D31: 385157 | E31: 290386 | F31: 236041 | G31: 407985 | H31: 184446 | I31: 342894 | J31: 180344 | K31: 292917 | L31: 314858 | M31: 364057

Sheet Q1_Lookups
A1: Q1 - LOOKUP FUNCTIONS (25 marks total)
A2: VLOOKUP · INDEX-MATCH · Two-way lookup · Chain lookup · Approximate lookup · Self-join
A4: Q# | B4: Question | C4: Marks | D4: Hint | E4: Your Answer | F4: Format
A5: Q1.1 | B5: For order ORD-00234, what is the customer_id? | C5: 3 | D5: Simple VLOOKUP on Orders sheet. | E5: =VLOOKUP("ORD-00234",Orders!A:K,3,FALSE) -> CUST-0173 | F5: CUST-####
A6: Q1.2 | B6: For order ORD-00456, what is the product_name? (You will need to look up the product_id first, then find its name in Products.) | C6: 3 | D6: Two-step lookup, or nested VLOOKUP. | E6: =VLOOKUP(VLOOKUP("ORD-00456",Orders!A:K,4,FALSE),Products!A:F,2,FALSE) -> Dumbbells 5kg | F6: Text
A7: Q1.3 | B7: For order ORD-00987, what is the rep_name of the sales rep? Note: the rep_name is in a column that appears to the LEFT of what you might look up first. | C7: 3 | D7: VLOOKUP has directional limits - INDEX/MATCH does not. | E7: =INDEX(Sales_Reps!B:B,MATCH(VLOOKUP("ORD-00987",Orders!A:K,5,FALSE),Sales_Reps!A:A,0)) -> Nisha Menon | F7: Text
A8: Q1.4 | B8: From the Targets sheet, what is the target value for rep R012 in the month Mar-24? | C8: 4 | D8: Two-way lookup: row = rep_id, column = month. | E8: =INDEX(Targets!A:M,MATCH("R012",Targets!A:A,0),MATCH("Mar-24",Targets!1:1,0)) -> 321255 | F8: Whole number
A9: Q1.5 | B9: For order ORD-01500, what is the CATEGORY of the product ordered? (Chain: order → product_id → category) | C9: 4 | D9: Multi-hop lookup across sheets. | E9: =VLOOKUP(VLOOKUP("ORD-01500",Orders!A:K,4,FALSE),Products!A:F,3,FALSE) -> Electronics | F9: Text
A10: Q1.6 | B10: For order ORD-00789, which DISCOUNT SLAB does it fall in? Use the slab table below (rows 20-24). Slab breakpoints are the LOWER bound of each range. | C10: 3 | D10: Approximate-match VLOOKUP (sort ascending, TRUE / omit last arg). | E10: =VLOOKUP(VLOOKUP("ORD-00789",Orders!A:K,8,FALSE),B18:C21,2,TRUE) -> Bronze | F10: Text
A11: Q1.7 | B11: For order ORD-01234, in one cell produce the string: "<rep_name> (<sales_region>)" - e.g. "Amit Singh (South)". | C11: 3 | D11: Two lookups joined with & or CONCATENATE. | E11: =VLOOKUP(VLOOKUP("ORD-01234",Orders!A:K,5,FALSE),Sales_Reps!A:C,2,FALSE)&" ("&VLOOKUP(VLOOKUP("ORD-01234",Orders!A:K,5,FALSE),Sales_Reps!A:C,3,FALSE)&")" -> Sanjay Kapoor (South) | F11: Text
A12: Q1.8 | B12: What is the rep_name of the TEAM LEAD for rep R017? (The Sales_Reps sheet has team_lead_id - you need to self-join to find that person's name.) | C12: 2 | D12: Look up the team_lead_id, then look up THAT id's rep_name. | E12: =VLOOKUP(VLOOKUP("R017",Sales_Reps!A:E,5,FALSE),Sales_Reps!A:B,2,FALSE) -> Amit Singh | F12: Text
B15: DISCOUNT SLAB REFERENCE TABLE (use for Q1.6)
B17: Discount % (Lower) | C17: Slab
B18: 0 | C18: Bronze
B19: 5 | C19: Silver
B20: 15 | C20: Gold
B21: 25 | C21: Platinum

Sheet Q2_Cleaning
A1: Q2 - DATA CLEANING & QUALITY DIAGNOSTICS (20 marks total)
A2: Duplicates · Whitespace · Case Inconsistency · Referential Integrity · Discontinued SKUs · Anomaly Patterns
A4: Q# | B4: Question | C4: Marks | D4: Hint | E4: Your Answer | F4: Format
A5: Q2.1 | B5: How many DUPLICATE rows exist in the Orders sheet (i.e., how many order_id values appear more than once)? Count each duplicate as ONE (not the extras). | C5: 3 | D5: COUNTIF > 1, then count. Watch what you're counting - rows or IDs. | E5: {=SUMPRODUCT((COUNTIF(Orders!A2:A2001,Orders!A2:A2001)>1)/COUNTIF(Orders!A2:A2001,Orders!A2:A2001))} -> 20 | F5: Whole number
A6: Q2.2 | B6: How many customers in the Customers sheet have LEADING or TRAILING whitespace in their customer_name? | C6: 3 | D6: Compare LEN vs LEN(TRIM). Or use SUMPRODUCT with a boolean. | E6: {=SUMPRODUCT(--(LEN(Customers!B2:B301)<>LEN(TRIM(Customers!B2:B301))))} -> 15 | F6: Whole number
A7: Q2.3 | B7: The Customers sheet has some cities in inconsistent case (e.g., "mumbai", "MUMBAI", "Mumbai"). How many DISTINCT cities exist AFTER standardizing case? | C7: 3 | D7: Combine PROPER/UPPER with a de-dup count. SUMPRODUCT + 1/COUNTIF trick works. | E7: {=COUNTA(_xlfn.UNIQUE(UPPER(Customers!D2:D301)))} -> 6 | F7: Whole number
A8: Q2.4 | B8: How many orders reference a customer_id that DOES NOT EXIST in the Customers sheet? (Broken foreign key) | C8: 4 | D8: Use MATCH with ISNA/ISERROR, then count. | E8: {=SUMPRODUCT(--ISNA(MATCH(Orders!C2:C2001,Customers!A2:A301,0)))} -> 30 | F8: Whole number
A9: Q2.5 | B9: How many orders reference a product that is currently DISCONTINUED (is_active = FALSE in the Products sheet)? | C9: 3 | D9: VLOOKUP the is_active flag, then count where FALSE. | E9: {=SUM(--(_xlfn.XLOOKUP(Orders!D2:D2001,Products!A2:A61,Products!F2:F61)=FALSE))} -> 174 | F9: Whole number
A10: Q2.6 | B10: Find the "suspicious pattern": how many orders have payment_status = "Cancelled" AND a discount_pct > 20%? (This pattern often indicates promo abuse - a real-world diagnostic query.) | C10: 4 | D10: COUNTIFS with two criteria. | E10: =COUNTIFS(Orders!J2:J2001,"Cancelled",Orders!H2:H2001,">20") -> 58 | F10: Whole number

Sheet Q3_Aggregation
A1: Q3 - CONDITIONAL AGGREGATION (25 marks total)
A2: SUMIFS · COUNTIFS · AVERAGEIFS · Nested IF logic · Multi-sheet aggregation · Top-N logic
A4: Q# | B4: Question | C4: Marks | D4: Hint | E4: Your Answer | F4: Format
A5: Q3.1 | B5: What is the TOTAL REVENUE (sum of final_amount) for orders in Q3 2024 (Jul-Sep) where ship_city is Mumbai? | C5: 4 | D5: SUMIFS with 3 conditions: date >= start, date <= end, city = Mumbai. Beware case issues. | E5: =SUMIFS(Orders!$I$2:$I$2001,Orders!$B$2:$B$2001,">="&DATE(2024,7,1),Orders!$B$2:$B$2001,"<"&DATE(2024,10,1),Orders!$K$2:$K$2001,"Mumbai") -> 1217239 | F5: Currency
A6: Q3.2 | B6: How many orders have discount_pct > 15% AND payment_status = "Completed"? | C6: 3 | D6: COUNTIFS with two conditions. | E6: =COUNTIFS(Orders!$H$2:$H$2001,">15",Orders!$J$2:$J$2001,"Completed") -> 723 | F6: Whole number
A7: Q3.3 | B7: What is the AVERAGE final_amount for orders where the product CATEGORY is "Electronics" AND the customer SEGMENT is "Corporate"? Note: Both fields come from OTHER sheets - you'll need helper columns. | C7: 5 | D7: Helper columns in Orders: VLOOKUP category from Products, VLOOKUP segment from Customers. Then AVERAGEIFS. | E7: =AVERAGEIFS(Orders!$I$2:$I$2001,Orders!$L$2:$L$2001,"Electronics",Orders!$M$2:$M$2001,"Corporate") -> 13981.402 | F7: Currency
A8: Q3.4 | B8: What is the COMBINED REVENUE of the TOP 3 reps by total revenue? (Sum of the 3 highest rep totals.) | C8: 4 | D8: Compute per-rep totals, then use SUMPRODUCT with LARGE, or sort and sum top 3. | E8: =LARGE(Sales_Reps!$I$2:$I$31,1)+LARGE(Sales_Reps!$I$2:$I$31,2)+LARGE(Sales_Reps!$I$2:$I$31,3) -> 3342678.5 | F8: Currency
A9: Q3.5 | B9: For rep R015 in Nov-24: compute the actual revenue and compare to the target (from Targets sheet). Report the PERFORMANCE TIER using: <80% → "Below", 80-120% → "On Track", >120% → "Exceeds". Return only the tier text. | C9: 5 | D9: Nested IF (or IFS): compute actual/target ratio, then classify. | E9: =_xlfn.LET(_xlpm.actual,SUMIFS(Orders!$I$2:$I$2001,Orders!$E$2:$E$2001,"R015",Orders!$B$2:$B$2001,">="&DATE(2024,11,1),Orders!$B$2:$B$2001,"<"&DATE(2024,12,1)),_xlpm.target,_xlfn.XLOOKUP("R015",Targets!$A:$A,Targets!$L:$L),_xlpm.ratio,_xlpm.actual/_xlpm.target,IF(_xlpm.ratio<80%,"Below",IF(_xlpm.ratio<=120%,"On Track","Exceeds"))) -> Below | F9: Text
A10: Q3.6 | B10: What is the TOTAL revenue from Corporate segment customers aged between 30 and 40 (both inclusive)? | C10: 4 | D10: Helper columns for age and segment. Then SUMIFS with numeric range. | E10: =SUMIFS(Orders!$I$2:$I$2001,Orders!$M$2:$M$2001,"Corporate",Orders!$N$2:$N$2001,">=30",Orders!$N$2:$N$2001,"<=40") -> 982568.4 | F10: Currency

Sheet Q4_Pivot
A1: Q4 - PIVOT TABLES (20 marks total)
A2: 2D Pivots · Filters · % of Row Total · Date Grouping · Calculated Fields · Cross-Sheet Data
A4: Q# | B4: Question | C4: Marks | D4: Hint | E4: Your Answer | F4: Format
A5: Q4.1 | B5: Build a pivot with sales_region as rows and product category as columns, values = SUM of final_amount. What value appears at the intersection of "South" and "Electronics"? | C5: 4 | D5: You need to add category (from Products) and region (from Sales_Reps) as columns to Orders first. Insert PivotTable from combined data. | E5: 1314107.4 | F5: Currency
A6: Q4.2 | B6: Build a pivot: rows = order month (Jan-24 through Dec-24), columns = sales_rep_id, values = SUM of final_amount. What is the HIGHEST single value in the entire pivot? (One number.) | C6: 4 | D6: After building, use MAX() over the pivot data range, or scan visually. | E6: 216421.52 | F6: Currency
A7: Q4.3 | B7: For the North sales_region only: what PERCENTAGE of total revenue comes from the Apparel category? Configure the pivot with Show Values As → % of Row Total. | C7: 4 | D7: Pivot: rows=region, cols=category, values=sum(final_amount), Show Values As = % of Row Total. | E7: 0.1402 | F7: Percentage
A8: Q4.4 | B8: Group order dates by QUARTER in a pivot. What is the total revenue for Q4 2024 (Oct-Dec)? | C8: 4 | D8: PivotTable → Group By → Quarter. Or SUMIFS with date range. | E8: =SUMIFS(Orders!$I$2:$I$2001,Orders!$B$2:$B$2001,">="&DATE(2024,10,1),Orders!$B$2:$B$2001,"<"&DATE(2025,1,1)) -> 6459443 | F8: Currency
A9: Q4.5 | B9: Create a CALCULATED FIELD in the pivot: profit_margin = (unit_price - unit_cost) / unit_price. What is the AVERAGE profit_margin for orders shipped to Delhi? Give as a percentage. | C9: 4 | D9: Add unit_cost via VLOOKUP as helper column. Create pivot calculated field, filter to Delhi. | E9: 0.4488 | F9: Percentage

Sheet Q5_Advanced
A1: Q5 - ADVANCED (10 marks total)
A2: RANK · Running Totals · TEXTJOIN · LARGE + INDEX/MATCH · Multi-condition top-N
A4: Q# | B4: Question | C4: Marks | D4: Hint | E4: Your Answer | F4: Format
A5: Q5.1 | B5: Rank all sales reps by total revenue (highest = rank 1). Who (name) is at RANK #7? | C5: 2 | D5: Per-rep totals, then use RANK.EQ, or sort. Return the rep_name at position 7. | E5: AMIT SINGH | F5: Text
A6: Q5.2 | B6: What is the CUMULATIVE revenue from Jan 2024 through the end of Aug 2024? (Sum of final_amount where order_date <= 31-Aug-2024.) | C6: 2 | D6: SUMIFS with date <=. | E6: =SUMIFS(Orders!$I$2:$I$2001,Orders!$B$2:$B$2001,">="&DATE(2024,1,1),Orders!$B$2:$B$2001,"<"&DATE(2024,9,1)) -> 18050690 | F6: Currency
A7: Q5.3 | B7: Among orders where the sales rep is in the WEST region: which product (by name) has the 2nd highest total revenue? | C7: 3 | D7: Helper: sales_region on orders. Filter/pivot to West, sum by product, rank, get #2, VLOOKUP product name. | E7: =VLOOKUP("PROD-003",Products!$A:$D,2,FALSE) -> Smart Watch | F7: Text
A8: Q5.4 | B8: Concatenate the names of the top 5 reps by revenue into a single cell, separated by " | " (space-pipe-space). | C8: 2 | D8: TEXTJOIN with delimiter " | ". Combine with LARGE to pull top 5. | E8: ="Neha Desai"&" | "&"Shalini Patel"&" | "&"Deepak Shah"&" | "&"Nisha Menon"&" | "&"Arun Iyer" -> Neha Desai | Shalini Patel | Deepak Shah | Nisha Menon | Arun Iyer | F8: Text
A9: Q5.5 | B9: What is the HIGHEST single order value (final_amount) where ship_city = "Bengaluru" AND the product's category = "Grocery"? | C9: 1 | D9: MAXIFS with a category helper column, or nested MAX(IF()). | E9: =_xlfn.AGGREGATE(14,6,Orders!$I$2:$I$2001/((Orders!$K$2:$K$2001="Bengaluru")*(Orders!$L$2:$L$2001="Grocery")),1) -> 22134 | F9: Currency
